{"settings":[{"key":"App_Version","valueType":"string","defaultValue":"0.00-0","configTitle":"App_Version_Title","configPrompt":null,"configType":"alphaNumeric","configError":null,"configHelpUrl":null,"configReadonly":true,"configRequired":false,"configOptions":null,"configMin":null,"configMax":null,"configMaxLength":null},{"key":"Duration_1","valueType":"number","defaultValue":5,"configTitle":"Duration_1_Title","configPrompt":null,"configType":"numeric","configError":null,"configHelpUrl":null,"configReadonly":false,"configRequired":false,"configOptions":null,"configMin":1,"configMax":3600,"configMaxLength":null},{"key":"Duration_2","valueType":"number","defaultValue":60,"configTitle":"Duration_2_Title","configPrompt":null,"configType":"numeric","configError":null,"configHelpUrl":null,"configReadonly":false,"configRequired":false,"configOptions":null,"configMin":0,"configMax":3600,"configMaxLength":null},{"key":"Duration_3","valueType":"number","defaultValue":300,"configTitle":"Duration_3_Title","configPrompt":null,"configType":"numeric","configError":null,"configHelpUrl":null,"configReadonly":false,"configRequired":false,"configOptions":null,"configMin":0,"configMax":3600,"configMaxLength":null},{"key":"Duration_4","valueType":"number","defaultValue":1200,"configTitle":"Duration_4_Title","configPrompt":null,"configType":"numeric","configError":null,"configHelpUrl":null,"configReadonly":false,"configRequired":false,"configOptions":null,"configMin":0,"configMax":3600,"configMaxLength":null}],"supportsLiveValidation":false,"languages":{"valyrian":{"Duration_2_Title":"Power Peak Duration 2","AppVersion":"1.07-1","Power_Unit":"W","DF_Title_Title":"Data Field Title","Duration_1_Title":"Power Peak Duration 1","Duration_3_Title":"Power Peak Duration 3","App_Version_Title":"Application Version","Duration_4_Title":"Power Peak Duration 4","AppName":"DF_PowerPeaks"}}}